ece_loss/__init__.py
ece_loss/loss.py
ece_loss-1.0.0.dist-info/LICENSE
ece_loss-1.0.0.dist-info/METADATA
ece_loss-1.0.0.dist-info/WHEEL
ece_loss-1.0.0.dist-info/top_level.txt
ece_loss-1.0.0.dist-info/RECORD
