Metadata-Version: 2.1
Name: ece-loss
Version: 1.0.0
Summary: UNKNOWN
Home-page: https://github.com/NKI-AI/ece_loss
Author: Jonas Teuwen
Author-email: j.teuwen@nki.nl
License: Apache Software License 2.0
Keywords: ece_loss
Platform: UNKNOWN
Classifier: Development Status :: 5 - Production/Stable
Classifier: Intended Audience :: Developers
Classifier: License :: OSI Approved :: Apache Software License
Classifier: Natural Language :: English
Classifier: Programming Language :: Python :: 3
Classifier: Programming Language :: Python :: 3.8
Classifier: Programming Language :: Python :: 3.9
Requires-Python: >=3.8
License-File: LICENSE
Requires-Dist: torch (~=1.9.0)
Requires-Dist: setuptools (~=58.0.4)
Provides-Extra: dev
Requires-Dist: numpy (~=1.21.2) ; extra == 'dev'
Requires-Dist: pytest ; extra == 'dev'
Requires-Dist: pylint ; extra == 'dev'
Requires-Dist: black ; extra == 'dev'
Requires-Dist: isort ; extra == 'dev'
Requires-Dist: tox ; extra == 'dev'
Provides-Extra: example
Requires-Dist: pillow (~=8.4.0) ; extra == 'example'
Requires-Dist: matplotlib (~=3.4.3) ; extra == 'example'
